{
  "eventId": "c1e65984-f87b-4a73-9024-8aa890d21759",
  "tenantId": "restaurant-onboarding-smoke",
  "workspaceId": "restaurant-autonomous-company-flow",
  "actorId": "ae-commandhub",
  "sourcePlatform": "ae-commandhub",
  "targetPlatform": "ae-commandhub",
  "eventType": "ae.requested",
  "payload": {
    "merchantId": "merchant-smoke-restaurant-001",
    "requestType": "autonomous-company-onboarding",
    "requiredCapabilities": [
      "jobs",
      "dispatch",
      "orders",
      "storefront"
    ]
  },
  "payloadHash": "01fee292241e3afbea1b42d7e2603d4307fb970f2c0e8d74eb2624972a2e82af",
  "createdAt": "2026-05-01T08:06:43.414Z",
  "replayNonce": "0e7d13e6ed1724fea21ea923c9c9fc9c"
}