{
  "eventId": "f87e94cd-5a38-4a46-8ffb-15b8d435db41",
  "tenantId": "restaurant-onboarding-smoke",
  "workspaceId": "restaurant-autonomous-company-flow",
  "actorId": "ae-commandhub",
  "sourcePlatform": "ae-commandhub",
  "targetPlatform": null,
  "eventType": "lead.generated",
  "payload": {
    "merchantId": "merchant-smoke-restaurant-001",
    "businessName": "Smoke Test Restaurant",
    "vertical": "restaurant",
    "market": "Phoenix",
    "wantsJobs": true,
    "wantsDispatch": true,
    "wantsStorefront": true,
    "wantsOrders": true,
    "leadId": "lead-smoke-restaurant-001",
    "source": "restaurant-onboarding"
  },
  "payloadHash": "2ed007ec248ca9da8d488b895849fcaee6139df9677d0f2c2aaff315fa057879",
  "createdAt": "2026-05-01T07:26:23.144Z",
  "replayNonce": "2896b098ac0f8f34e3e37e51a46415e2"
}