{
  "version": 1,
  "required": [
    "source",
    "sourceChecksum",
    "importedAt",
    "compatibility"
  ],
  "generatedAt": "2026-04-16T07:39:20.061Z",
  "totalTemplates": 1,
  "completeTemplates": 1,
  "entries": [
    {
      "templateId": "donor-template-0001",
      "donorAsset": "skydexia/knowledge-base/GiftsFromtheSkyes/1776323952764-import-fixture.txt",
      "metadataAsset": "skydexia/knowledge-base/GiftsFromtheSkyes/1776323952764-import-fixture.txt.meta.json",
      "coverage": {
        "source": true,
        "sourceChecksum": true,
        "importedAt": true,
        "compatibility": true
      },
      "complete": true
    }
  ],
  "missing": []
}
