{
  "started_at": "2026-05-01T07:09:44.387Z",
  "checks": [
    {
      "status": "PASS",
      "name": "health_reports_v0_3_0",
      "data": {
        "ok": true,
        "app": "SkyeRoutexFlow Workforce Command",
        "version": "0.4.0",
        "database_driver": "local-json",
        "storage_driver": "local-json",
        "production_mode": false
      }
    },
    {
      "status": "PASS",
      "name": "html_has_login-form",
      "data": {}
    },
    {
      "status": "PASS",
      "name": "html_has_signup-form",
      "data": {}
    },
    {
      "status": "PASS",
      "name": "html_has_market-form",
      "data": {}
    },
    {
      "status": "PASS",
      "name": "html_has_job-form",
      "data": {}
    },
    {
      "status": "PASS",
      "name": "html_has_feed-form",
      "data": {}
    },
    {
      "status": "PASS",
      "name": "html_has_provider-jobs",
      "data": {}
    },
    {
      "status": "PASS",
      "name": "html_has_applicant-pool",
      "data": {}
    },
    {
      "status": "PASS",
      "name": "html_has_contractor-feed",
      "data": {}
    },
    {
      "status": "PASS",
      "name": "html_has_assignments",
      "data": {}
    },
    {
      "status": "PASS",
      "name": "html_has_routes",
      "data": {}
    },
    {
      "status": "PASS",
      "name": "html_has_roster",
      "data": {}
    },
    {
      "status": "PASS",
      "name": "html_has_ratings",
      "data": {}
    },
    {
      "status": "PASS",
      "name": "html_has_operator-assign-form",
      "data": {}
    },
    {
      "status": "PASS",
      "name": "html_has_rating-form",
      "data": {}
    },
    {
      "status": "PASS",
      "name": "html_has_house-jobs",
      "data": {}
    },
    {
      "status": "PASS",
      "name": "html_has_payments",
      "data": {}
    },
    {
      "status": "PASS",
      "name": "html_has_audits",
      "data": {}
    },
    {
      "status": "PASS",
      "name": "app_js_wires__api_provider_jobs",
      "data": {}
    },
    {
      "status": "PASS",
      "name": "app_js_wires__api_assignments",
      "data": {}
    },
    {
      "status": "PASS",
      "name": "app_js_wires__api_jobs_b_dataset_job_accept_applicant",
      "data": {}
    },
    {
      "status": "PASS",
      "name": "app_js_wires__api_assignments_id_action_",
      "data": {}
    },
    {
      "status": "PASS",
      "name": "app_js_wires__api_autonomous_recommend_",
      "data": {}
    },
    {
      "status": "PASS",
      "name": "app_js_wires__api_house_command_freeze_payment",
      "data": {}
    },
    {
      "status": "PASS",
      "name": "app_js_wires__api_route_jobs",
      "data": {}
    },
    {
      "status": "PASS",
      "name": "app_js_wires__api_provider_roster",
      "data": {}
    },
    {
      "status": "PASS",
      "name": "app_js_wires__api_house_command_assign",
      "data": {}
    },
    {
      "status": "PASS",
      "name": "app_js_wires__api_ratings",
      "data": {}
    },
    {
      "status": "PASS",
      "name": "panels_are_scrollable",
      "data": {}
    }
  ],
  "server_log_excerpt": "server spawned with stdio ignored for deterministic smoke exit."
}